{
	"packs": {
		"cubecraft": {
			"name": "CubeCraft Moddée",
			"version": 1,
			"install": {
				"url": "https://drive.charreyron.fr/d/s/sZKVPVY80s6p46yvLeMGGqcOjcIEFB0l/webapi/entry.cgi/cubecraft%20test.zip?api=SYNO.SynologyDrive.Files&method=download&version=2&files=%5B%22id%3A738716793662651607%22%5D&force_download=true&json_error=true&c2_offload=%22allow%22&_dc=1677623642962&sharing_token=%22gWrrjtYb6WWoeTIAiJrv_eo8xMCiYlIHcYoPcziWVKiv3VQZBuXxFkrtidgZT.ho6zS6fLyVW2Yumq7zYNABo3x0QOsUW0rP0W8MhvAqXVoiweX0SlM.ngHZgBn2WHRgxjYySbb3dITR9gV5EYXAeePZf4xCGP_8wr8_iIF9znwu.VbZrKJP38VtS1BWoOnqXLi_FJp__3mSqpNAuT4BXOi0XcBohH_hGWYYrkK2cqqYr0pN_Sfhn53w%22&SynoToken=paB91GjIm8wBg",
				"hash": "cccd817ac851a795149ba6560b8603a9df3b1b93",
				"verify": ["libraries", "natives", "minecraft.jar"]
			},
			"launch": {
				"jvmflags": ["-XX:+IgnoreUnrecognizedVMOptions", "-XstartOnFirstThread", "-Xmx2G", "-XX:+UseG1GC", "-XX:+UnlockExperimentalVMOptions", "-XX:G1NewSizePercent=20", "-XX:G1ReservePercent=20", "-XX:MaxGCPauseMillis=50", "-XX:G1HeapRegionSize=32M"],
				"jvmflags_default": ["-Xmx1280M"],
				"jvmflags_64": ["-Xmx2G"],
				"natives": "natives",
				"libraries": "libraries",
				"jar": "minecraft.jar",
				"main": "cp.mo.mo.Launcher",
				"assets": "assets",
				"args": ["--tweakClass", "optifine.OptiFineTweaker"]
			}	
		}
	}
}
